mporm/__init__.py
mporm/convert.py
mporm/dsn.py
mporm/executor.py
mporm/expr.py
mporm/fields.py
mporm/model.py
mporm/model_test.py
mporm/oper.py
mporm/schema.py
mporm/sql.py
mporm/sql_test.py
mporm/time.py
mporm-0.0.2.dist-info/LICENSE
mporm-0.0.2.dist-info/METADATA
mporm-0.0.2.dist-info/WHEEL
mporm-0.0.2.dist-info/top_level.txt
mporm-0.0.2.dist-info/RECORD
