Metadata-Version: 2.1
Name: mporm
Version: 0.0.2
Summary: MySQL ORM in Python
Home-page: https://github.com/mivinci/mporm
Author: Leonard Mivinci XJJ
Author-email: 1366723936@qq.com
License: UNKNOWN
Platform: UNKNOWN
Classifier: Programming Language :: Python :: 3
Classifier: License :: OSI Approved :: MIT License
Classifier: Operating System :: OS Independent
Requires-Dist: PyMySQL
Requires-Dist: toml
